<?xml version="1.0" encoding="UTF-8"?><ri:Resource xmlns:ri="http://www.ivoa.net/xml/RegistryInterface/v1.0" xmlns:oai="http://www.openarchives.org/OAI/2.0/" xmlns:xsi="http://www.w3.org/2001/XMLSchema-instance" xmlns:cea="http://www.ivoa.net/xml/CEA/v1.0rc1" xmlns:va="http://www.ivoa.net/xml/VOApplication/v1.0rc1" xmlns:vg="http://www.ivoa.net/xml/VORegistry/v1.0" xmlns:vr="http://www.ivoa.net/xml/VOResource/v1.0" xmlns:vs="http://www.ivoa.net/xml/VODataService/v1.0" created="2000-01-01T09:00:00" status="active" updated="2009-09-23T12:31:36" xsi:type="vr:Organisation" xsi:schemaLocation="http://www.ivoa.net/xml/RegistryInterface/v1.0 http://software.astrogrid.org/schema/registry/RegistryInterface/v1.0/RegistryInterface.xsd http://www.ivoa.net/xml/VOResource/v1.0 http://software.astrogrid.org/schema/vo-resource-types/VOResource/v1.0/VOResource.xsd  http://www.ivoa.net/xml/VODataService/v1.0 http://software.astrogrid.org/schema/vo-resource-types/VODataService/v1.0/VODataService.xsd http://www.ivoa.net/xml/VOTable/v1.0 http://software.astrogrid.org/schema/vo-formats/VOTable/v1.0/VOTable.xsd http://www.ivoa.net/xml/ConeSearch/v1.0 http://software.astrogrid.org/schema/vo-resource-types/ConeSearch/v1.0/ConeSearch.xsd http://www.ivoa.net/xml/SIA/v1.0 http://software.astrogrid.org/schema/vo-resource-types/SIA/v1.0/SIA.xsd http://www.ivoa.net/xml/SSA/v0.4 http://software.astrogrid.org/schema/vo-resource-types/SSA/v0.4/SSA.xsd urn:astrogrid:schema:vo-resource-types:STAP:v1.0 http://software.astrogrid.org/schema/vo-resource-types/STAP/v1.0/STAP.xsd http://www.ivoa.net/xml/CEA/v1.0rc1 http://software.astrogrid.org/schema/vo-resource-types/CEAService/v1.0rc1/CEAService.xsd">
        <title>Special Astrophysical Observatory of RAS (SAO RAS)</title>
        <identifier>ivo://sao.ru/organisation</identifier>
        <curation>
            <publisher>Special Astrophysical Observatory of RAS (SAO RAS)</publisher>
            <creator>
                <name/>
                <logo>http://www.sao.ru/Images/saologo.gif</logo>
            </creator>
            <contact>
                <name>Olga Zhelenkova</name>
                <email>zhe@sao.ru</email>
            </contact>
        </curation>
        <content>
            <subject>Organisation</subject>
            <description>Special Astrophysical Observatory of RAS (SAO RAS) Public Registry</description>
            <referenceURL>http://www.sao.ru/astrogrid-registry</referenceURL>
            <type>Organisation</type>
            <contentLevel>Research</contentLevel>
        </content>
        <facility>Registry</facility>
    </ri:Resource>